cmi_docx/__init__.py
cmi_docx/comment.py
cmi_docx/document.py
cmi_docx/paragraph.py
cmi_docx/run.py
cmi_docx/styles.py
cmi_docx/table.py
cmi_docx-0.4.2.dist-info/METADATA
cmi_docx-0.4.2.dist-info/WHEEL
cmi_docx-0.4.2.dist-info/licenses/LICENSE
cmi_docx-0.4.2.dist-info/RECORD
