Metadata-Version: 2.4
Name: cmi-docx
Version: 0.4.2
Summary: Additional tooling for Python-docx.
License-File: LICENSE
Requires-Python: >=3.10
Requires-Dist: python-docx>=1.1.2
